app/__init__.py
app/cli.py
app/config.py
app/runner.py
app/user_config_manager.py
app/data/disposable_domains.json
app/services/__init__.py
app/services/checker.py
app/services/loader.py
app/utils/__init__.py
app/utils/update_disposable_domains.py
app/validators/__init__.py
app/validators/ascii_check.py
app/validators/disposable_check.py
app/validators/dns_utils.py
app/validators/regex_check.py
app/validators/smtp_check.py
email_checker_mv-0.4.0.dist-info/licenses/LICENSE
email_checker_mv-0.4.0.dist-info/METADATA
email_checker_mv-0.4.0.dist-info/WHEEL
email_checker_mv-0.4.0.dist-info/entry_points.txt
email_checker_mv-0.4.0.dist-info/top_level.txt
email_checker_mv-0.4.0.dist-info/RECORD
