Metadata-Version: 2.4
Name: email-checker-mv
Version: 0.4.0
Summary: Batch and CLI email validator
Author-email: Mykola Vuy <mykola.vuy@gmail.com>
License: MIT
Requires-Python: >=3.8
License-File: LICENSE
Requires-Dist: pandas
Requires-Dist: dnspython
Requires-Dist: email-validator
Requires-Dist: requests
Dynamic: license-file
